typehints_cleo2/__init__.py
typehints_cleo2/utils.py
typehints_cleo2-1.0.0.dist-info/LICENSE
typehints_cleo2-1.0.0.dist-info/METADATA
typehints_cleo2-1.0.0.dist-info/WHEEL
typehints_cleo2-1.0.0.dist-info/RECORD
