Metadata-Version: 2.1
Name: typehints_cleo2
Version: 1.0.0
Summary: Type-Hinted, Type-Enforced classes for cleo 2.x
Home-page: https://github.com/RAVoigt/typehints_cleo2
License: MIT
Author: Rob Voigt
Author-email: code@ravoigt.com
Requires-Python: >=3.11,<4.0
Classifier: License :: OSI Approved :: MIT License
Classifier: Programming Language :: Python :: 3
Classifier: Programming Language :: Python :: 3.11
Classifier: Programming Language :: Python :: 3.12
Requires-Dist: cleo (>=2.1.0,<3.0.0)
Project-URL: Repository, https://github.com/RAVoigt/typehints_cleo2
